uscan_notify/main.py
uscan_notify/versions.py
uscan_notify-0.1.1.dist-info/LICENSE
uscan_notify-0.1.1.dist-info/METADATA
uscan_notify-0.1.1.dist-info/WHEEL
uscan_notify-0.1.1.dist-info/entry_points.txt
uscan_notify-0.1.1.dist-info/RECORD
