Metadata-Version: 2.1
Name: uscan-notify
Version: 0.1.1
Summary: Notify when uscan detects new upstream versions.
License: MIT
Author: Maytham Alsudany
Author-email: maytha8thedev@gmail.com
Requires-Python: >=3.11,<4.0
Classifier: License :: OSI Approved :: MIT License
Classifier: Programming Language :: Python :: 3
Classifier: Programming Language :: Python :: 3.11
Classifier: Programming Language :: Python :: 3.12
Requires-Dist: click (>=8.1.7,<9.0.0)
Requires-Dist: platformdirs (>=4.0.0,<5.0.0)
Requires-Dist: requests (>=2.31.0,<3.0.0)
